.bzrignore
AUTHOR.txt
CHANGES.txt
README.txt
bootstrap.py
buildout.cfg
setup.cfg
setup.py
docs/Makefile
docs/api.rst
docs/changes.rst
docs/conf.py
docs/glossary.rst
docs/index.rst
docs/usage.rst
docs/.static/logo_hi.gif
docs/.static/repoze.css
src/repoze/__init__.py
src/repoze.formapi.egg-info/PKG-INFO
src/repoze.formapi.egg-info/SOURCES.txt
src/repoze.formapi.egg-info/dependency_links.txt
src/repoze.formapi.egg-info/namespace_packages.txt
src/repoze.formapi.egg-info/not-zip-safe
src/repoze.formapi.egg-info/requires.txt
src/repoze.formapi.egg-info/top_level.txt
src/repoze/formapi/README.txt
src/repoze/formapi/__init__.py
src/repoze/formapi/error.py
src/repoze/formapi/form.py
src/repoze/formapi/parser.py
src/repoze/formapi/py24.py
src/repoze/formapi/tests.py