Metadata-Version: 1.1
Name: repoze.formapi
Version: 0.6
Summary: Minimalistic form library.
Home-page: UNKNOWN
Author: Malthe Borch
Author-email: repoze-dev@lists.repoze.org
License: BSD-derived (http://www.repoze.org/LICENSE.txt)
Keywords: forms html validation marshalling
Platform: UNKNOWN
Classifier: Development Status :: 5 - Production/Stable
Classifier: Environment :: Web Environment
Classifier: Intended Audience :: Developers
Classifier: License :: OSI Approved :: Zope Public License
Classifier: Programming Language :: Python
Classifier: Natural Language :: English
Classifier: Operating System :: OS Independent
Classifier: Topic :: Internet :: WWW/HTTP
